katalytic/checks.py
katalytic_checks-0.1.1.dist-info/LICENSE.txt
katalytic_checks-0.1.1.dist-info/WHEEL
katalytic_checks-0.1.1.dist-info/METADATA
katalytic_checks-0.1.1.dist-info/RECORD
