Metadata-Version: 2.1
Name: katalytic-checks
Version: 0.1.1
Summary: This plugin adds utilities for working with data to the katalytic namespace
Keywords: high-level,data conversion
Author-email: Valentin Neagu <vali19th@protonmail.com>
Requires-Python: >=3.6
Classifier: Development Status :: 3 - Alpha
Classifier: Intended Audience :: Developers
Classifier: Intended Audience :: System Administrators
Classifier: License :: OSI Approved :: MIT License
Classifier: Natural Language :: English
Classifier: Operating System :: OS Independent
Classifier: Programming Language :: Python :: 3
Classifier: Topic :: Software Development :: Libraries
Classifier: Topic :: Utilities
Requires-Dist: katalytic-pkg>=0.2.6
Requires-Dist: katalytic-data>=0.7.1 ; extra == "dev"
Requires-Dist: pytest ; extra == "dev"
Requires-Dist: pytest-cov ; extra == "dev"
Requires-Dist: pytest-randomly ; extra == "dev"
Project-URL: homepage, https://gitlab.com/katalytic/katalytic-checks.git
Project-URL: repository, https://gitlab.com/katalytic/katalytic-checks.git
Provides-Extra: dev
